README
setup.py
PyCogWorks.egg-info/PKG-INFO
PyCogWorks.egg-info/SOURCES.txt
PyCogWorks.egg-info/dependency_links.txt
PyCogWorks.egg-info/top_level.txt
pycogworks/__init__.py
pycogworks/cogworld.py
pycogworks/cwsubject.py
pycogworks/eyegaze.py
pycogworks/fixation.py
pycogworks/logging.py
pycogworks/nback.py
pycogworks/questionnaire.py
pycogworks/util.py